tatl
fastbuf
tatlrt
